{
  "by_state": [
    {
      "SP_STATE_CODE": 5,
      "n_fills": 162129,
      "n_patients": 7321,
      "pct_late": 76.1,
      "mean_risk": 0.525,
      "n_high": 88814,
      "n_mod": 44103,
      "n_low": 29212,
      "pct_high": 54.8
    },
    {
      "SP_STATE_CODE": 10,
      "n_fills": 104216,
      "n_patients": 4760,
      "pct_late": 76.4,
      "mean_risk": 0.527,
      "n_high": 57386,
      "n_mod": 28434,
      "n_low": 18396,
      "pct_high": 55.1
    },
    {
      "SP_STATE_CODE": 33,
      "n_fills": 92334,
      "n_patients": 4095,
      "pct_late": 75.9,
      "mean_risk": 0.524,
      "n_high": 50510,
      "n_mod": 25058,
      "n_low": 16766,
      "pct_high": 54.7
    },
    {
      "SP_STATE_CODE": 45,
      "n_fills": 90949,
      "n_patients": 4072,
      "pct_late": 76.2,
      "mean_risk": 0.524,
      "n_high": 49993,
      "n_mod": 24237,
      "n_low": 16719,
      "pct_high": 55.0
    },
    {
      "SP_STATE_CODE": 39,
      "n_fills": 77543,
      "n_patients": 3489,
      "pct_late": 76.3,
      "mean_risk": 0.526,
      "n_high": 42617,
      "n_mod": 21081,
      "n_low": 13845,
      "pct_high": 55.0
    },
    {
      "SP_STATE_CODE": 14,
      "n_fills": 56195,
      "n_patients": 2556,
      "pct_late": 76.1,
      "mean_risk": 0.524,
      "n_high": 30795,
      "n_mod": 15152,
      "n_low": 10248,
      "pct_high": 54.8
    },
    {
      "SP_STATE_CODE": 36,
      "n_fills": 53648,
      "n_patients": 2491,
      "pct_late": 76.1,
      "mean_risk": 0.526,
      "n_high": 29570,
      "n_mod": 14471,
      "n_low": 9607,
      "pct_high": 55.1
    },
    {
      "SP_STATE_CODE": 34,
      "n_fills": 49539,
      "n_patients": 2176,
      "pct_late": 76.2,
      "mean_risk": 0.523,
      "n_high": 27188,
      "n_mod": 13153,
      "n_low": 9198,
      "pct_high": 54.9
    },
    {
      "SP_STATE_CODE": 23,
      "n_fills": 46496,
      "n_patients": 2229,
      "pct_late": 76.3,
      "mean_risk": 0.527,
      "n_high": 25659,
      "n_mod": 12608,
      "n_low": 8229,
      "pct_high": 55.2
    },
    {
      "SP_STATE_CODE": 31,
      "n_fills": 40268,
      "n_patients": 1794,
      "pct_late": 76.0,
      "mean_risk": 0.522,
      "n_high": 21918,
      "n_mod": 10899,
      "n_low": 7451,
      "pct_high": 54.4
    },
    {
      "SP_STATE_CODE": 11,
      "n_fills": 40149,
      "n_patients": 1731,
      "pct_late": 75.9,
      "mean_risk": 0.524,
      "n_high": 22055,
      "n_mod": 10657,
      "n_low": 7437,
      "pct_high": 54.9
    },
    {
      "SP_STATE_CODE": 44,
      "n_fills": 38596,
      "n_patients": 1637,
      "pct_late": 76.2,
      "mean_risk": 0.524,
      "n_high": 21194,
      "n_mod": 10342,
      "n_low": 7060,
      "pct_high": 54.9
    },
    {
      "SP_STATE_CODE": 26,
      "n_fills": 34247,
      "n_patients": 1495,
      "pct_late": 75.9,
      "mean_risk": 0.523,
      "n_high": 18603,
      "n_mod": 9421,
      "n_low": 6223,
      "pct_high": 54.3
    },
    {
      "SP_STATE_CODE": 49,
      "n_fills": 34032,
      "n_patients": 1525,
      "pct_late": 76.1,
      "mean_risk": 0.523,
      "n_high": 18667,
      "n_mod": 9036,
      "n_low": 6329,
      "pct_high": 54.9
    },
    {
      "SP_STATE_CODE": 15,
      "n_fills": 31960,
      "n_patients": 1407,
      "pct_late": 75.6,
      "mean_risk": 0.522,
      "n_high": 17421,
      "n_mod": 8535,
      "n_low": 6004,
      "pct_high": 54.5
    },
    {
      "SP_STATE_CODE": 22,
      "n_fills": 30671,
      "n_patients": 1472,
      "pct_late": 76.7,
      "mean_risk": 0.529,
      "n_high": 17067,
      "n_mod": 8366,
      "n_low": 5238,
      "pct_high": 55.6
    },
    {
      "SP_STATE_CODE": 50,
      "n_fills": 27679,
      "n_patients": 1275,
      "pct_late": 76.2,
      "mean_risk": 0.524,
      "n_high": 15232,
      "n_mod": 7345,
      "n_low": 5102,
      "pct_high": 55.0
    },
    {
      "SP_STATE_CODE": 1,
      "n_fills": 26951,
      "n_patients": 1233,
      "pct_late": 76.4,
      "mean_risk": 0.524,
      "n_high": 14906,
      "n_mod": 7033,
      "n_low": 5012,
      "pct_high": 55.3
    },
    {
      "SP_STATE_CODE": 3,
      "n_fills": 26770,
      "n_patients": 1307,
      "pct_late": 76.0,
      "mean_risk": 0.527,
      "n_high": 14691,
      "n_mod": 7422,
      "n_low": 4657,
      "pct_high": 54.9
    },
    {
      "SP_STATE_CODE": 24,
      "n_fills": 25923,
      "n_patients": 1252,
      "pct_late": 76.9,
      "mean_risk": 0.528,
      "n_high": 14298,
      "n_mod": 7240,
      "n_low": 4385,
      "pct_high": 55.2
    },
    {
      "SP_STATE_CODE": 18,
      "n_fills": 25915,
      "n_patients": 1094,
      "pct_late": 76.2,
      "mean_risk": 0.524,
      "n_high": 14314,
      "n_mod": 6743,
      "n_low": 4858,
      "pct_high": 55.2
    },
    {
      "SP_STATE_CODE": 52,
      "n_fills": 24728,
      "n_patients": 1167,
      "pct_late": 76.1,
      "mean_risk": 0.525,
      "n_high": 13631,
      "n_mod": 6574,
      "n_low": 4523,
      "pct_high": 55.1
    },
    {
      "SP_STATE_CODE": 54,
      "n_fills": 24159,
      "n_patients": 1050,
      "pct_late": 76.1,
      "mean_risk": 0.527,
      "n_high": 13418,
      "n_mod": 6364,
      "n_low": 4377,
      "pct_high": 55.5
    },
    {
      "SP_STATE_CODE": 19,
      "n_fills": 23036,
      "n_patients": 1032,
      "pct_late": 76.2,
      "mean_risk": 0.526,
      "n_high": 12780,
      "n_mod": 6111,
      "n_low": 4145,
      "pct_high": 55.5
    },
    {
      "SP_STATE_CODE": 42,
      "n_fills": 21775,
      "n_patients": 988,
      "pct_late": 76.3,
      "mean_risk": 0.524,
      "n_high": 11908,
      "n_mod": 5948,
      "n_low": 3919,
      "pct_high": 54.7
    },
    {
      "SP_STATE_CODE": 21,
      "n_fills": 18839,
      "n_patients": 881,
      "pct_late": 76.8,
      "mean_risk": 0.527,
      "n_high": 10505,
      "n_mod": 5002,
      "n_low": 3332,
      "pct_high": 55.8
    },
    {
      "SP_STATE_CODE": 37,
      "n_fills": 18403,
      "n_patients": 841,
      "pct_late": 76.2,
      "mean_risk": 0.524,
      "n_high": 10155,
      "n_mod": 4937,
      "n_low": 3311,
      "pct_high": 55.2
    },
    {
      "SP_STATE_CODE": 25,
      "n_fills": 18268,
      "n_patients": 752,
      "pct_late": 75.8,
      "mean_risk": 0.523,
      "n_high": 10054,
      "n_mod": 4843,
      "n_low": 3371,
      "pct_high": 55.0
    },
    {
      "SP_STATE_CODE": 38,
      "n_fills": 17786,
      "n_patients": 879,
      "pct_late": 76.0,
      "mean_risk": 0.523,
      "n_high": 9638,
      "n_mod": 4919,
      "n_low": 3229,
      "pct_high": 54.2
    },
    {
      "SP_STATE_CODE": 16,
      "n_fills": 17625,
      "n_patients": 815,
      "pct_late": 76.4,
      "mean_risk": 0.524,
      "n_high": 9653,
      "n_mod": 4789,
      "n_low": 3183,
      "pct_high": 54.8
    },
    {
      "SP_STATE_CODE": 4,
      "n_fills": 17256,
      "n_patients": 806,
      "pct_late": 75.9,
      "mean_risk": 0.523,
      "n_high": 9483,
      "n_mod": 4512,
      "n_low": 3261,
      "pct_high": 55.0
    },
    {
      "SP_STATE_CODE": 6,
      "n_fills": 17231,
      "n_patients": 899,
      "pct_late": 77.0,
      "mean_risk": 0.53,
      "n_high": 9557,
      "n_mod": 4795,
      "n_low": 2879,
      "pct_high": 55.5
    },
    {
      "SP_STATE_CODE": 7,
      "n_fills": 16015,
      "n_patients": 748,
      "pct_late": 76.1,
      "mean_risk": 0.524,
      "n_high": 8766,
      "n_mod": 4370,
      "n_low": 2879,
      "pct_high": 54.7
    },
    {
      "SP_STATE_CODE": 17,
      "n_fills": 15911,
      "n_patients": 705,
      "pct_late": 76.0,
      "mean_risk": 0.523,
      "n_high": 8791,
      "n_mod": 4161,
      "n_low": 2959,
      "pct_high": 55.3
    },
    {
      "SP_STATE_CODE": 51,
      "n_fills": 13868,
      "n_patients": 591,
      "pct_late": 75.8,
      "mean_risk": 0.526,
      "n_high": 7642,
      "n_mod": 3721,
      "n_low": 2505,
      "pct_high": 55.1
    },
    {
      "SP_STATE_CODE": 28,
      "n_fills": 10054,
      "n_patients": 433,
      "pct_late": 75.7,
      "mean_risk": 0.521,
      "n_high": 5412,
      "n_mod": 2766,
      "n_low": 1876,
      "pct_high": 53.8
    },
    {
      "SP_STATE_CODE": 20,
      "n_fills": 9002,
      "n_patients": 390,
      "pct_late": 75.2,
      "mean_risk": 0.517,
      "n_high": 4869,
      "n_mod": 2345,
      "n_low": 1788,
      "pct_high": 54.1
    },
    {
      "SP_STATE_CODE": 32,
      "n_fills": 8461,
      "n_patients": 428,
      "pct_late": 75.8,
      "mean_risk": 0.525,
      "n_high": 4645,
      "n_mod": 2288,
      "n_low": 1528,
      "pct_high": 54.9
    },
    {
      "SP_STATE_CODE": 29,
      "n_fills": 8438,
      "n_patients": 434,
      "pct_late": 76.4,
      "mean_risk": 0.528,
      "n_high": 4635,
      "n_mod": 2348,
      "n_low": 1455,
      "pct_high": 54.9
    },
    {
      "SP_STATE_CODE": 46,
      "n_fills": 7781,
      "n_patients": 381,
      "pct_late": 76.2,
      "mean_risk": 0.524,
      "n_high": 4237,
      "n_mod": 2147,
      "n_low": 1397,
      "pct_high": 54.5
    },
    {
      "SP_STATE_CODE": 13,
      "n_fills": 6285,
      "n_patients": 325,
      "pct_late": 76.7,
      "mean_risk": 0.527,
      "n_high": 3457,
      "n_mod": 1731,
      "n_low": 1097,
      "pct_high": 55.0
    },
    {
      "SP_STATE_CODE": 41,
      "n_fills": 5777,
      "n_patients": 282,
      "pct_late": 76.5,
      "mean_risk": 0.527,
      "n_high": 3191,
      "n_mod": 1565,
      "n_low": 1021,
      "pct_high": 55.2
    },
    {
      "SP_STATE_CODE": 12,
      "n_fills": 5699,
      "n_patients": 297,
      "pct_late": 76.2,
      "mean_risk": 0.529,
      "n_high": 3101,
      "n_mod": 1679,
      "n_low": 919,
      "pct_high": 54.4
    },
    {
      "SP_STATE_CODE": 30,
      "n_fills": 5443,
      "n_patients": 273,
      "pct_late": 75.7,
      "mean_risk": 0.529,
      "n_high": 3018,
      "n_mod": 1520,
      "n_low": 905,
      "pct_high": 55.4
    },
    {
      "SP_STATE_CODE": 43,
      "n_fills": 4927,
      "n_patients": 223,
      "pct_late": 76.5,
      "mean_risk": 0.526,
      "n_high": 2690,
      "n_mod": 1355,
      "n_low": 882,
      "pct_high": 54.6
    },
    {
      "SP_STATE_CODE": 8,
      "n_fills": 4387,
      "n_patients": 189,
      "pct_late": 74.9,
      "mean_risk": 0.515,
      "n_high": 2384,
      "n_mod": 1128,
      "n_low": 875,
      "pct_high": 54.3
    },
    {
      "SP_STATE_CODE": 27,
      "n_fills": 4166,
      "n_patients": 211,
      "pct_late": 77.2,
      "mean_risk": 0.531,
      "n_high": 2338,
      "n_mod": 1147,
      "n_low": 681,
      "pct_high": 56.1
    },
    {
      "SP_STATE_CODE": 35,
      "n_fills": 3665,
      "n_patients": 185,
      "pct_late": 76.4,
      "mean_risk": 0.525,
      "n_high": 2018,
      "n_mod": 990,
      "n_low": 657,
      "pct_high": 55.1
    },
    {
      "SP_STATE_CODE": 47,
      "n_fills": 3098,
      "n_patients": 163,
      "pct_late": 75.6,
      "mean_risk": 0.524,
      "n_high": 1691,
      "n_mod": 831,
      "n_low": 576,
      "pct_high": 54.6
    },
    {
      "SP_STATE_CODE": 53,
      "n_fills": 2075,
      "n_patients": 118,
      "pct_late": 75.7,
      "mean_risk": 0.53,
      "n_high": 1160,
      "n_mod": 559,
      "n_low": 356,
      "pct_high": 55.9
    },
    {
      "SP_STATE_CODE": 9,
      "n_fills": 1991,
      "n_patients": 113,
      "pct_late": 77.3,
      "mean_risk": 0.536,
      "n_high": 1137,
      "n_mod": 544,
      "n_low": 310,
      "pct_high": 57.1
    },
    {
      "SP_STATE_CODE": 2,
      "n_fills": 1236,
      "n_patients": 75,
      "pct_late": 78.6,
      "mean_risk": 0.53,
      "n_high": 674,
      "n_mod": 370,
      "n_low": 192,
      "pct_high": 54.5
    }
  ],
  "by_county": [
    {
      "SP_STATE_CODE": 5,
      "BENE_COUNTY_CD": 200,
      "n_fills": 37305,
      "n_patients": 1692,
      "pct_late": 76.1,
      "mean_risk": 0.525,
      "n_high": 20468,
      "pct_high": 54.9
    },
    {
      "SP_STATE_CODE": 14,
      "BENE_COUNTY_CD": 141,
      "n_fills": 21268,
      "n_patients": 961,
      "pct_late": 75.9,
      "mean_risk": 0.525,
      "n_high": 11686,
      "pct_high": 54.9
    },
    {
      "SP_STATE_CODE": 5,
      "BENE_COUNTY_CD": 470,
      "n_fills": 15212,
      "n_patients": 656,
      "pct_late": 76.5,
      "mean_risk": 0.524,
      "n_high": 8250,
      "pct_high": 54.2
    },
    {
      "SP_STATE_CODE": 5,
      "BENE_COUNTY_CD": 400,
      "n_fills": 14449,
      "n_patients": 612,
      "pct_late": 75.8,
      "mean_risk": 0.522,
      "n_high": 7867,
      "pct_high": 54.4
    },
    {
      "SP_STATE_CODE": 3,
      "BENE_COUNTY_CD": 60,
      "n_fills": 13823,
      "n_patients": 665,
      "pct_late": 75.8,
      "mean_risk": 0.526,
      "n_high": 7533,
      "pct_high": 54.5
    },
    {
      "SP_STATE_CODE": 10,
      "BENE_COUNTY_CD": 120,
      "n_fills": 11360,
      "n_patients": 531,
      "pct_late": 76.0,
      "mean_risk": 0.525,
      "n_high": 6197,
      "pct_high": 54.6
    },
    {
      "SP_STATE_CODE": 45,
      "BENE_COUNTY_CD": 610,
      "n_fills": 10791,
      "n_patients": 535,
      "pct_late": 75.9,
      "mean_risk": 0.526,
      "n_high": 5910,
      "pct_high": 54.8
    },
    {
      "SP_STATE_CODE": 33,
      "BENE_COUNTY_CD": 331,
      "n_fills": 9861,
      "n_patients": 425,
      "pct_late": 76.1,
      "mean_risk": 0.526,
      "n_high": 5405,
      "pct_high": 54.8
    },
    {
      "SP_STATE_CODE": 39,
      "BENE_COUNTY_CD": 10,
      "n_fills": 9419,
      "n_patients": 397,
      "pct_late": 76.5,
      "mean_risk": 0.524,
      "n_high": 5117,
      "pct_high": 54.3
    },
    {
      "SP_STATE_CODE": 5,
      "BENE_COUNTY_CD": 430,
      "n_fills": 9096,
      "n_patients": 422,
      "pct_late": 76.5,
      "mean_risk": 0.529,
      "n_high": 5016,
      "pct_high": 55.1
    },
    {
      "SP_STATE_CODE": 33,
      "BENE_COUNTY_CD": 590,
      "n_fills": 8546,
      "n_patients": 374,
      "pct_late": 75.3,
      "mean_risk": 0.521,
      "n_high": 4657,
      "pct_high": 54.5
    },
    {
      "SP_STATE_CODE": 23,
      "BENE_COUNTY_CD": 810,
      "n_fills": 8216,
      "n_patients": 401,
      "pct_late": 76.6,
      "mean_risk": 0.529,
      "n_high": 4574,
      "pct_high": 55.7
    },
    {
      "SP_STATE_CODE": 33,
      "BENE_COUNTY_CD": 420,
      "n_fills": 8178,
      "n_patients": 338,
      "pct_late": 75.1,
      "mean_risk": 0.518,
      "n_high": 4372,
      "pct_high": 53.5
    },
    {
      "SP_STATE_CODE": 10,
      "BENE_COUNTY_CD": 490,
      "n_fills": 8078,
      "n_patients": 365,
      "pct_late": 76.5,
      "mean_risk": 0.531,
      "n_high": 4534,
      "pct_high": 56.1
    },
    {
      "SP_STATE_CODE": 39,
      "BENE_COUNTY_CD": 620,
      "n_fills": 7739,
      "n_patients": 343,
      "pct_late": 75.6,
      "mean_risk": 0.521,
      "n_high": 4217,
      "pct_high": 54.5
    },
    {
      "SP_STATE_CODE": 10,
      "BENE_COUNTY_CD": 50,
      "n_fills": 7430,
      "n_patients": 342,
      "pct_late": 76.6,
      "mean_risk": 0.526,
      "n_high": 4077,
      "pct_high": 54.9
    },
    {
      "SP_STATE_CODE": 50,
      "BENE_COUNTY_CD": 160,
      "n_fills": 7316,
      "n_patients": 331,
      "pct_late": 76.1,
      "mean_risk": 0.521,
      "n_high": 3968,
      "pct_high": 54.2
    },
    {
      "SP_STATE_CODE": 45,
      "BENE_COUNTY_CD": 390,
      "n_fills": 7274,
      "n_patients": 342,
      "pct_late": 78.6,
      "mean_risk": 0.531,
      "n_high": 4070,
      "pct_high": 56.0
    },
    {
      "SP_STATE_CODE": 36,
      "BENE_COUNTY_CD": 170,
      "n_fills": 7141,
      "n_patients": 303,
      "pct_late": 76.0,
      "mean_risk": 0.527,
      "n_high": 3950,
      "pct_high": 55.3
    },
    {
      "SP_STATE_CODE": 33,
      "BENE_COUNTY_CD": 700,
      "n_fills": 7064,
      "n_patients": 310,
      "pct_late": 75.8,
      "mean_risk": 0.523,
      "n_high": 3831,
      "pct_high": 54.2
    },
    {
      "SP_STATE_CODE": 45,
      "BENE_COUNTY_CD": 130,
      "n_fills": 6998,
      "n_patients": 301,
      "pct_late": 76.3,
      "mean_risk": 0.522,
      "n_high": 3796,
      "pct_high": 54.2
    },
    {
      "SP_STATE_CODE": 33,
      "BENE_COUNTY_CD": 400,
      "n_fills": 6997,
      "n_patients": 321,
      "pct_late": 75.4,
      "mean_risk": 0.524,
      "n_high": 3834,
      "pct_high": 54.8
    },
    {
      "SP_STATE_CODE": 5,
      "BENE_COUNTY_CD": 440,
      "n_fills": 6991,
      "n_patients": 301,
      "pct_late": 76.1,
      "mean_risk": 0.527,
      "n_high": 3863,
      "pct_high": 55.3
    },
    {
      "SP_STATE_CODE": 5,
      "BENE_COUNTY_CD": 460,
      "n_fills": 6880,
      "n_patients": 324,
      "pct_late": 76.2,
      "mean_risk": 0.524,
      "n_high": 3782,
      "pct_high": 55.0
    },
    {
      "SP_STATE_CODE": 10,
      "BENE_COUNTY_CD": 510,
      "n_fills": 6858,
      "n_patients": 303,
      "pct_late": 76.1,
      "mean_risk": 0.527,
      "n_high": 3796,
      "pct_high": 55.4
    },
    {
      "SP_STATE_CODE": 22,
      "BENE_COUNTY_CD": 90,
      "n_fills": 6541,
      "n_patients": 309,
      "pct_late": 76.5,
      "mean_risk": 0.529,
      "n_high": 3627,
      "pct_high": 55.5
    },
    {
      "SP_STATE_CODE": 5,
      "BENE_COUNTY_CD": 530,
      "n_fills": 6087,
      "n_patients": 297,
      "pct_late": 75.7,
      "mean_risk": 0.524,
      "n_high": 3329,
      "pct_high": 54.7
    },
    {
      "SP_STATE_CODE": 5,
      "BENE_COUNTY_CD": 0,
      "n_fills": 5860,
      "n_patients": 272,
      "pct_late": 75.3,
      "mean_risk": 0.522,
      "n_high": 3163,
      "pct_high": 54.0
    },
    {
      "SP_STATE_CODE": 26,
      "BENE_COUNTY_CD": 940,
      "n_fills": 5543,
      "n_patients": 247,
      "pct_late": 77.0,
      "mean_risk": 0.528,
      "n_high": 3075,
      "pct_high": 55.5
    },
    {
      "SP_STATE_CODE": 29,
      "BENE_COUNTY_CD": 10,
      "n_fills": 5471,
      "n_patients": 275,
      "pct_late": 76.2,
      "mean_risk": 0.525,
      "n_high": 2998,
      "pct_high": 54.8
    },
    {
      "SP_STATE_CODE": 45,
      "BENE_COUNTY_CD": 910,
      "n_fills": 5324,
      "n_patients": 235,
      "pct_late": 76.3,
      "mean_risk": 0.527,
      "n_high": 2983,
      "pct_high": 56.0
    },
    {
      "SP_STATE_CODE": 5,
      "BENE_COUNTY_CD": 60,
      "n_fills": 5216,
      "n_patients": 234,
      "pct_late": 76.7,
      "mean_risk": 0.527,
      "n_high": 2876,
      "pct_high": 55.1
    },
    {
      "SP_STATE_CODE": 24,
      "BENE_COUNTY_CD": 260,
      "n_fills": 5202,
      "n_patients": 249,
      "pct_late": 77.1,
      "mean_risk": 0.533,
      "n_high": 2920,
      "pct_high": 56.1
    },
    {
      "SP_STATE_CODE": 33,
      "BENE_COUNTY_CD": 240,
      "n_fills": 5122,
      "n_patients": 246,
      "pct_late": 77.5,
      "mean_risk": 0.53,
      "n_high": 2865,
      "pct_high": 55.9
    },
    {
      "SP_STATE_CODE": 54,
      "BENE_COUNTY_CD": 999,
      "n_fills": 4964,
      "n_patients": 231,
      "pct_late": 74.7,
      "mean_risk": 0.529,
      "n_high": 2769,
      "pct_high": 55.8
    },
    {
      "SP_STATE_CODE": 7,
      "BENE_COUNTY_CD": 10,
      "n_fills": 4747,
      "n_patients": 207,
      "pct_late": 76.1,
      "mean_risk": 0.525,
      "n_high": 2608,
      "pct_high": 54.9
    },
    {
      "SP_STATE_CODE": 33,
      "BENE_COUNTY_CD": 800,
      "n_fills": 4687,
      "n_patients": 202,
      "pct_late": 76.0,
      "mean_risk": 0.522,
      "n_high": 2547,
      "pct_high": 54.3
    },
    {
      "SP_STATE_CODE": 33,
      "BENE_COUNTY_CD": 20,
      "n_fills": 4667,
      "n_patients": 214,
      "pct_late": 76.8,
      "mean_risk": 0.528,
      "n_high": 2617,
      "pct_high": 56.1
    },
    {
      "SP_STATE_CODE": 39,
      "BENE_COUNTY_CD": 560,
      "n_fills": 4655,
      "n_patients": 204,
      "pct_late": 75.4,
      "mean_risk": 0.526,
      "n_high": 2553,
      "pct_high": 54.8
    },
    {
      "SP_STATE_CODE": 23,
      "BENE_COUNTY_CD": 620,
      "n_fills": 4648,
      "n_patients": 222,
      "pct_late": 75.6,
      "mean_risk": 0.528,
      "n_high": 2573,
      "pct_high": 55.4
    },
    {
      "SP_STATE_CODE": 10,
      "BENE_COUNTY_CD": 280,
      "n_fills": 4358,
      "n_patients": 219,
      "pct_late": 76.1,
      "mean_risk": 0.526,
      "n_high": 2408,
      "pct_high": 55.3
    },
    {
      "SP_STATE_CODE": 18,
      "BENE_COUNTY_CD": 550,
      "n_fills": 4336,
      "n_patients": 178,
      "pct_late": 76.6,
      "mean_risk": 0.526,
      "n_high": 2406,
      "pct_high": 55.5
    },
    {
      "SP_STATE_CODE": 31,
      "BENE_COUNTY_CD": 100,
      "n_fills": 4184,
      "n_patients": 195,
      "pct_late": 76.1,
      "mean_risk": 0.526,
      "n_high": 2281,
      "pct_high": 54.5
    },
    {
      "SP_STATE_CODE": 10,
      "BENE_COUNTY_CD": 40,
      "n_fills": 4087,
      "n_patients": 179,
      "pct_late": 76.2,
      "mean_risk": 0.526,
      "n_high": 2239,
      "pct_high": 54.8
    },
    {
      "SP_STATE_CODE": 10,
      "BENE_COUNTY_CD": 630,
      "n_fills": 4087,
      "n_patients": 177,
      "pct_late": 76.4,
      "mean_risk": 0.528,
      "n_high": 2247,
      "pct_high": 55.0
    },
    {
      "SP_STATE_CODE": 10,
      "BENE_COUNTY_CD": 150,
      "n_fills": 4069,
      "n_patients": 177,
      "pct_late": 76.5,
      "mean_risk": 0.525,
      "n_high": 2227,
      "pct_high": 54.7
    },
    {
      "SP_STATE_CODE": 5,
      "BENE_COUNTY_CD": 480,
      "n_fills": 4065,
      "n_patients": 184,
      "pct_late": 77.0,
      "mean_risk": 0.53,
      "n_high": 2259,
      "pct_high": 55.6
    },
    {
      "SP_STATE_CODE": 31,
      "BENE_COUNTY_CD": 310,
      "n_fills": 4051,
      "n_patients": 189,
      "pct_late": 75.7,
      "mean_risk": 0.526,
      "n_high": 2214,
      "pct_high": 54.7
    },
    {
      "SP_STATE_CODE": 44,
      "BENE_COUNTY_CD": 780,
      "n_fills": 4026,
      "n_patients": 173,
      "pct_late": 76.5,
      "mean_risk": 0.53,
      "n_high": 2257,
      "pct_high": 56.1
    },
    {
      "SP_STATE_CODE": 7,
      "BENE_COUNTY_CD": 40,
      "n_fills": 4010,
      "n_patients": 180,
      "pct_late": 75.2,
      "mean_risk": 0.52,
      "n_high": 2174,
      "pct_high": 54.2
    },
    {
      "SP_STATE_CODE": 10,
      "BENE_COUNTY_CD": 470,
      "n_fills": 4008,
      "n_patients": 191,
      "pct_late": 77.6,
      "mean_risk": 0.532,
      "n_high": 2234,
      "pct_high": 55.7
    },
    {
      "SP_STATE_CODE": 5,
      "BENE_COUNTY_CD": 140,
      "n_fills": 3991,
      "n_patients": 154,
      "pct_late": 75.7,
      "mean_risk": 0.521,
      "n_high": 2148,
      "pct_high": 53.8
    },
    {
      "SP_STATE_CODE": 10,
      "BENE_COUNTY_CD": 350,
      "n_fills": 3985,
      "n_patients": 174,
      "pct_late": 75.7,
      "mean_risk": 0.525,
      "n_high": 2195,
      "pct_high": 55.1
    },
    {
      "SP_STATE_CODE": 3,
      "BENE_COUNTY_CD": 90,
      "n_fills": 3927,
      "n_patients": 228,
      "pct_late": 77.8,
      "mean_risk": 0.531,
      "n_high": 2179,
      "pct_high": 55.5
    },
    {
      "SP_STATE_CODE": 15,
      "BENE_COUNTY_CD": 480,
      "n_fills": 3853,
      "n_patients": 175,
      "pct_late": 75.9,
      "mean_risk": 0.525,
      "n_high": 2093,
      "pct_high": 54.3
    },
    {
      "SP_STATE_CODE": 33,
      "BENE_COUNTY_CD": 370,
      "n_fills": 3835,
      "n_patients": 160,
      "pct_late": 76.0,
      "mean_risk": 0.526,
      "n_high": 2110,
      "pct_high": 55.0
    },
    {
      "SP_STATE_CODE": 36,
      "BENE_COUNTY_CD": 250,
      "n_fills": 3822,
      "n_patients": 173,
      "pct_late": 76.6,
      "mean_risk": 0.53,
      "n_high": 2109,
      "pct_high": 55.2
    },
    {
      "SP_STATE_CODE": 12,
      "BENE_COUNTY_CD": 20,
      "n_fills": 3801,
      "n_patients": 204,
      "pct_late": 76.9,
      "mean_risk": 0.532,
      "n_high": 2070,
      "pct_high": 54.5
    },
    {
      "SP_STATE_CODE": 1,
      "BENE_COUNTY_CD": 360,
      "n_fills": 3760,
      "n_patients": 183,
      "pct_late": 75.6,
      "mean_risk": 0.525,
      "n_high": 2043,
      "pct_high": 54.3
    },
    {
      "SP_STATE_CODE": 10,
      "BENE_COUNTY_CD": 570,
      "n_fills": 3746,
      "n_patients": 170,
      "pct_late": 76.1,
      "mean_risk": 0.523,
      "n_high": 2054,
      "pct_high": 54.8
    },
    {
      "SP_STATE_CODE": 23,
      "BENE_COUNTY_CD": 490,
      "n_fills": 3712,
      "n_patients": 184,
      "pct_late": 76.3,
      "mean_risk": 0.527,
      "n_high": 2083,
      "pct_high": 56.1
    },
    {
      "SP_STATE_CODE": 39,
      "BENE_COUNTY_CD": 140,
      "n_fills": 3690,
      "n_patients": 161,
      "pct_late": 75.7,
      "mean_risk": 0.526,
      "n_high": 2035,
      "pct_high": 55.1
    },
    {
      "SP_STATE_CODE": 5,
      "BENE_COUNTY_CD": 660,
      "n_fills": 3632,
      "n_patients": 177,
      "pct_late": 75.7,
      "mean_risk": 0.522,
      "n_high": 1967,
      "pct_high": 54.2
    },
    {
      "SP_STATE_CODE": 41,
      "BENE_COUNTY_CD": 30,
      "n_fills": 3622,
      "n_patients": 167,
      "pct_late": 76.4,
      "mean_risk": 0.524,
      "n_high": 1982,
      "pct_high": 54.7
    },
    {
      "SP_STATE_CODE": 14,
      "BENE_COUNTY_CD": 250,
      "n_fills": 3581,
      "n_patients": 162,
      "pct_late": 77.0,
      "mean_risk": 0.53,
      "n_high": 2011,
      "pct_high": 56.2
    },
    {
      "SP_STATE_CODE": 31,
      "BENE_COUNTY_CD": 270,
      "n_fills": 3567,
      "n_patients": 146,
      "pct_late": 77.4,
      "mean_risk": 0.518,
      "n_high": 1909,
      "pct_high": 53.5
    },
    {
      "SP_STATE_CODE": 7,
      "BENE_COUNTY_CD": 0,
      "n_fills": 3524,
      "n_patients": 177,
      "pct_late": 77.5,
      "mean_risk": 0.528,
      "n_high": 1938,
      "pct_high": 55.0
    },
    {
      "SP_STATE_CODE": 26,
      "BENE_COUNTY_CD": 470,
      "n_fills": 3488,
      "n_patients": 164,
      "pct_late": 77.8,
      "mean_risk": 0.53,
      "n_high": 1949,
      "pct_high": 55.9
    },
    {
      "SP_STATE_CODE": 22,
      "BENE_COUNTY_CD": 40,
      "n_fills": 3440,
      "n_patients": 171,
      "pct_late": 77.3,
      "mean_risk": 0.533,
      "n_high": 1936,
      "pct_high": 56.3
    },
    {
      "SP_STATE_CODE": 5,
      "BENE_COUNTY_CD": 510,
      "n_fills": 3434,
      "n_patients": 151,
      "pct_late": 77.1,
      "mean_risk": 0.529,
      "n_high": 1937,
      "pct_high": 56.4
    },
    {
      "SP_STATE_CODE": 36,
      "BENE_COUNTY_CD": 310,
      "n_fills": 3402,
      "n_patients": 163,
      "pct_late": 75.8,
      "mean_risk": 0.529,
      "n_high": 1948,
      "pct_high": 57.3
    },
    {
      "SP_STATE_CODE": 10,
      "BENE_COUNTY_CD": 520,
      "n_fills": 3381,
      "n_patients": 153,
      "pct_late": 75.4,
      "mean_risk": 0.528,
      "n_high": 1843,
      "pct_high": 54.5
    },
    {
      "SP_STATE_CODE": 34,
      "BENE_COUNTY_CD": 590,
      "n_fills": 3372,
      "n_patients": 137,
      "pct_late": 76.5,
      "mean_risk": 0.524,
      "n_high": 1878,
      "pct_high": 55.7
    },
    {
      "SP_STATE_CODE": 37,
      "BENE_COUNTY_CD": 540,
      "n_fills": 3359,
      "n_patients": 154,
      "pct_late": 75.7,
      "mean_risk": 0.519,
      "n_high": 1808,
      "pct_high": 53.8
    },
    {
      "SP_STATE_CODE": 10,
      "BENE_COUNTY_CD": 500,
      "n_fills": 3347,
      "n_patients": 142,
      "pct_late": 75.2,
      "mean_risk": 0.527,
      "n_high": 1847,
      "pct_high": 55.2
    },
    {
      "SP_STATE_CODE": 5,
      "BENE_COUNTY_CD": 90,
      "n_fills": 3313,
      "n_patients": 167,
      "pct_late": 76.5,
      "mean_risk": 0.529,
      "n_high": 1828,
      "pct_high": 55.2
    },
    {
      "SP_STATE_CODE": 11,
      "BENE_COUNTY_CD": 290,
      "n_fills": 3294,
      "n_patients": 123,
      "pct_late": 75.6,
      "mean_risk": 0.52,
      "n_high": 1805,
      "pct_high": 54.8
    },
    {
      "SP_STATE_CODE": 52,
      "BENE_COUNTY_CD": 390,
      "n_fills": 3287,
      "n_patients": 170,
      "pct_late": 75.1,
      "mean_risk": 0.528,
      "n_high": 1819,
      "pct_high": 55.3
    },
    {
      "SP_STATE_CODE": 22,
      "BENE_COUNTY_CD": 170,
      "n_fills": 3272,
      "n_patients": 159,
      "pct_late": 76.4,
      "mean_risk": 0.531,
      "n_high": 1817,
      "pct_high": 55.5
    },
    {
      "SP_STATE_CODE": 24,
      "BENE_COUNTY_CD": 610,
      "n_fills": 3261,
      "n_patients": 143,
      "pct_late": 76.7,
      "mean_risk": 0.522,
      "n_high": 1748,
      "pct_high": 53.6
    },
    {
      "SP_STATE_CODE": 4,
      "BENE_COUNTY_CD": 590,
      "n_fills": 3251,
      "n_patients": 127,
      "pct_late": 75.5,
      "mean_risk": 0.519,
      "n_high": 1797,
      "pct_high": 55.3
    },
    {
      "SP_STATE_CODE": 34,
      "BENE_COUNTY_CD": 910,
      "n_fills": 3235,
      "n_patients": 143,
      "pct_late": 76.5,
      "mean_risk": 0.523,
      "n_high": 1782,
      "pct_high": 55.1
    },
    {
      "SP_STATE_CODE": 21,
      "BENE_COUNTY_CD": 20,
      "n_fills": 3232,
      "n_patients": 166,
      "pct_late": 77.4,
      "mean_risk": 0.534,
      "n_high": 1834,
      "pct_high": 56.7
    },
    {
      "SP_STATE_CODE": 50,
      "BENE_COUNTY_CD": 260,
      "n_fills": 3219,
      "n_patients": 149,
      "pct_late": 75.3,
      "mean_risk": 0.522,
      "n_high": 1754,
      "pct_high": 54.5
    },
    {
      "SP_STATE_CODE": 22,
      "BENE_COUNTY_CD": 20,
      "n_fills": 3126,
      "n_patients": 137,
      "pct_late": 74.7,
      "mean_risk": 0.52,
      "n_high": 1692,
      "pct_high": 54.1
    },
    {
      "SP_STATE_CODE": 31,
      "BENE_COUNTY_CD": 290,
      "n_fills": 3121,
      "n_patients": 136,
      "pct_late": 76.8,
      "mean_risk": 0.523,
      "n_high": 1678,
      "pct_high": 53.8
    },
    {
      "SP_STATE_CODE": 22,
      "BENE_COUNTY_CD": 130,
      "n_fills": 3087,
      "n_patients": 147,
      "pct_late": 77.4,
      "mean_risk": 0.527,
      "n_high": 1695,
      "pct_high": 54.9
    },
    {
      "SP_STATE_CODE": 45,
      "BENE_COUNTY_CD": 480,
      "n_fills": 3063,
      "n_patients": 135,
      "pct_late": 76.0,
      "mean_risk": 0.518,
      "n_high": 1634,
      "pct_high": 53.3
    },
    {
      "SP_STATE_CODE": 31,
      "BENE_COUNTY_CD": 200,
      "n_fills": 2984,
      "n_patients": 128,
      "pct_late": 75.2,
      "mean_risk": 0.52,
      "n_high": 1644,
      "pct_high": 55.1
    },
    {
      "SP_STATE_CODE": 14,
      "BENE_COUNTY_CD": 570,
      "n_fills": 2965,
      "n_patients": 131,
      "pct_late": 76.1,
      "mean_risk": 0.527,
      "n_high": 1641,
      "pct_high": 55.3
    },
    {
      "SP_STATE_CODE": 21,
      "BENE_COUNTY_CD": 150,
      "n_fills": 2942,
      "n_patients": 125,
      "pct_late": 76.1,
      "mean_risk": 0.517,
      "n_high": 1603,
      "pct_high": 54.5
    },
    {
      "SP_STATE_CODE": 22,
      "BENE_COUNTY_CD": 160,
      "n_fills": 2921,
      "n_patients": 134,
      "pct_late": 77.7,
      "mean_risk": 0.529,
      "n_high": 1640,
      "pct_high": 56.1
    },
    {
      "SP_STATE_CODE": 36,
      "BENE_COUNTY_CD": 580,
      "n_fills": 2901,
      "n_patients": 142,
      "pct_late": 75.9,
      "mean_risk": 0.527,
      "n_high": 1593,
      "pct_high": 54.9
    },
    {
      "SP_STATE_CODE": 39,
      "BENE_COUNTY_CD": 800,
      "n_fills": 2888,
      "n_patients": 125,
      "pct_late": 76.8,
      "mean_risk": 0.527,
      "n_high": 1587,
      "pct_high": 55.0
    },
    {
      "SP_STATE_CODE": 46,
      "BENE_COUNTY_CD": 170,
      "n_fills": 2883,
      "n_patients": 132,
      "pct_late": 75.4,
      "mean_risk": 0.521,
      "n_high": 1546,
      "pct_high": 53.6
    },
    {
      "SP_STATE_CODE": 38,
      "BENE_COUNTY_CD": 250,
      "n_fills": 2852,
      "n_patients": 122,
      "pct_late": 77.0,
      "mean_risk": 0.521,
      "n_high": 1561,
      "pct_high": 54.7
    },
    {
      "SP_STATE_CODE": 10,
      "BENE_COUNTY_CD": 340,
      "n_fills": 2847,
      "n_patients": 130,
      "pct_late": 77.3,
      "mean_risk": 0.535,
      "n_high": 1596,
      "pct_high": 56.1
    },
    {
      "SP_STATE_CODE": 49,
      "BENE_COUNTY_CD": 290,
      "n_fills": 2830,
      "n_patients": 111,
      "pct_late": 75.0,
      "mean_risk": 0.517,
      "n_high": 1534,
      "pct_high": 54.2
    },
    {
      "SP_STATE_CODE": 28,
      "BENE_COUNTY_CD": 270,
      "n_fills": 2817,
      "n_patients": 106,
      "pct_late": 77.4,
      "mean_risk": 0.523,
      "n_high": 1530,
      "pct_high": 54.3
    },
    {
      "SP_STATE_CODE": 39,
      "BENE_COUNTY_CD": 770,
      "n_fills": 2815,
      "n_patients": 127,
      "pct_late": 77.7,
      "mean_risk": 0.532,
      "n_high": 1596,
      "pct_high": 56.7
    },
    {
      "SP_STATE_CODE": 11,
      "BENE_COUNTY_CD": 370,
      "n_fills": 2795,
      "n_patients": 113,
      "pct_late": 75.7,
      "mean_risk": 0.52,
      "n_high": 1543,
      "pct_high": 55.2
    },
    {
      "SP_STATE_CODE": 39,
      "BENE_COUNTY_CD": 290,
      "n_fills": 2777,
      "n_patients": 140,
      "pct_late": 76.8,
      "mean_risk": 0.529,
      "n_high": 1545,
      "pct_high": 55.6
    },
    {
      "SP_STATE_CODE": 39,
      "BENE_COUNTY_CD": 110,
      "n_fills": 2756,
      "n_patients": 113,
      "pct_late": 75.3,
      "mean_risk": 0.522,
      "n_high": 1529,
      "pct_high": 55.5
    },
    {
      "SP_STATE_CODE": 11,
      "BENE_COUNTY_CD": 470,
      "n_fills": 2751,
      "n_patients": 127,
      "pct_late": 76.0,
      "mean_risk": 0.531,
      "n_high": 1522,
      "pct_high": 55.3
    },
    {
      "SP_STATE_CODE": 50,
      "BENE_COUNTY_CD": 300,
      "n_fills": 2744,
      "n_patients": 126,
      "pct_late": 75.4,
      "mean_risk": 0.524,
      "n_high": 1520,
      "pct_high": 55.4
    },
    {
      "SP_STATE_CODE": 44,
      "BENE_COUNTY_CD": 180,
      "n_fills": 2734,
      "n_patients": 120,
      "pct_late": 76.8,
      "mean_risk": 0.529,
      "n_high": 1506,
      "pct_high": 55.1
    },
    {
      "SP_STATE_CODE": 37,
      "BENE_COUNTY_CD": 710,
      "n_fills": 2720,
      "n_patients": 130,
      "pct_late": 76.7,
      "mean_risk": 0.528,
      "n_high": 1516,
      "pct_high": 55.7
    },
    {
      "SP_STATE_CODE": 33,
      "BENE_COUNTY_CD": 520,
      "n_fills": 2714,
      "n_patients": 108,
      "pct_late": 75.3,
      "mean_risk": 0.52,
      "n_high": 1487,
      "pct_high": 54.8
    },
    {
      "SP_STATE_CODE": 10,
      "BENE_COUNTY_CD": 410,
      "n_fills": 2702,
      "n_patients": 126,
      "pct_late": 74.7,
      "mean_risk": 0.535,
      "n_high": 1551,
      "pct_high": 57.4
    },
    {
      "SP_STATE_CODE": 22,
      "BENE_COUNTY_CD": 70,
      "n_fills": 2649,
      "n_patients": 133,
      "pct_late": 77.8,
      "mean_risk": 0.531,
      "n_high": 1481,
      "pct_high": 55.9
    },
    {
      "SP_STATE_CODE": 39,
      "BENE_COUNTY_CD": 440,
      "n_fills": 2648,
      "n_patients": 129,
      "pct_late": 76.2,
      "mean_risk": 0.531,
      "n_high": 1486,
      "pct_high": 56.1
    },
    {
      "SP_STATE_CODE": 44,
      "BENE_COUNTY_CD": 460,
      "n_fills": 2625,
      "n_patients": 111,
      "pct_late": 76.6,
      "mean_risk": 0.525,
      "n_high": 1445,
      "pct_high": 55.0
    },
    {
      "SP_STATE_CODE": 36,
      "BENE_COUNTY_CD": 770,
      "n_fills": 2607,
      "n_patients": 112,
      "pct_late": 75.8,
      "mean_risk": 0.521,
      "n_high": 1472,
      "pct_high": 56.5
    },
    {
      "SP_STATE_CODE": 21,
      "BENE_COUNTY_CD": 30,
      "n_fills": 2587,
      "n_patients": 108,
      "pct_late": 75.6,
      "mean_risk": 0.525,
      "n_high": 1464,
      "pct_high": 56.6
    },
    {
      "SP_STATE_CODE": 31,
      "BENE_COUNTY_CD": 150,
      "n_fills": 2583,
      "n_patients": 108,
      "pct_late": 73.9,
      "mean_risk": 0.511,
      "n_high": 1378,
      "pct_high": 53.3
    },
    {
      "SP_STATE_CODE": 17,
      "BENE_COUNTY_CD": 450,
      "n_fills": 2576,
      "n_patients": 120,
      "pct_late": 76.4,
      "mean_risk": 0.525,
      "n_high": 1425,
      "pct_high": 55.3
    },
    {
      "SP_STATE_CODE": 34,
      "BENE_COUNTY_CD": 400,
      "n_fills": 2574,
      "n_patients": 124,
      "pct_late": 75.9,
      "mean_risk": 0.521,
      "n_high": 1374,
      "pct_high": 53.4
    },
    {
      "SP_STATE_CODE": 6,
      "BENE_COUNTY_CD": 150,
      "n_fills": 2563,
      "n_patients": 117,
      "pct_late": 76.9,
      "mean_risk": 0.524,
      "n_high": 1404,
      "pct_high": 54.8
    },
    {
      "SP_STATE_CODE": 5,
      "BENE_COUNTY_CD": 490,
      "n_fills": 2531,
      "n_patients": 115,
      "pct_late": 76.9,
      "mean_risk": 0.536,
      "n_high": 1458,
      "pct_high": 57.6
    },
    {
      "SP_STATE_CODE": 17,
      "BENE_COUNTY_CD": 860,
      "n_fills": 2507,
      "n_patients": 108,
      "pct_late": 75.8,
      "mean_risk": 0.528,
      "n_high": 1410,
      "pct_high": 56.2
    },
    {
      "SP_STATE_CODE": 23,
      "BENE_COUNTY_CD": 400,
      "n_fills": 2506,
      "n_patients": 120,
      "pct_late": 76.5,
      "mean_risk": 0.519,
      "n_high": 1356,
      "pct_high": 54.1
    },
    {
      "SP_STATE_CODE": 31,
      "BENE_COUNTY_CD": 230,
      "n_fills": 2449,
      "n_patients": 109,
      "pct_late": 76.8,
      "mean_risk": 0.527,
      "n_high": 1373,
      "pct_high": 56.1
    },
    {
      "SP_STATE_CODE": 19,
      "BENE_COUNTY_CD": 250,
      "n_fills": 2441,
      "n_patients": 106,
      "pct_late": 75.3,
      "mean_risk": 0.515,
      "n_high": 1334,
      "pct_high": 54.6
    },
    {
      "SP_STATE_CODE": 32,
      "BENE_COUNTY_CD": 0,
      "n_fills": 2441,
      "n_patients": 128,
      "pct_late": 76.7,
      "mean_risk": 0.524,
      "n_high": 1320,
      "pct_high": 54.1
    },
    {
      "SP_STATE_CODE": 36,
      "BENE_COUNTY_CD": 780,
      "n_fills": 2411,
      "n_patients": 116,
      "pct_late": 75.9,
      "mean_risk": 0.525,
      "n_high": 1315,
      "pct_high": 54.5
    },
    {
      "SP_STATE_CODE": 23,
      "BENE_COUNTY_CD": 240,
      "n_fills": 2341,
      "n_patients": 109,
      "pct_late": 76.2,
      "mean_risk": 0.521,
      "n_high": 1278,
      "pct_high": 54.6
    },
    {
      "SP_STATE_CODE": 45,
      "BENE_COUNTY_CD": 940,
      "n_fills": 2331,
      "n_patients": 99,
      "pct_late": 73.3,
      "mean_risk": 0.513,
      "n_high": 1245,
      "pct_high": 53.4
    },
    {
      "SP_STATE_CODE": 31,
      "BENE_COUNTY_CD": 370,
      "n_fills": 2315,
      "n_patients": 109,
      "pct_late": 77.8,
      "mean_risk": 0.531,
      "n_high": 1293,
      "pct_high": 55.9
    },
    {
      "SP_STATE_CODE": 33,
      "BENE_COUNTY_CD": 610,
      "n_fills": 2279,
      "n_patients": 103,
      "pct_late": 76.1,
      "mean_risk": 0.524,
      "n_high": 1201,
      "pct_high": 52.7
    },
    {
      "SP_STATE_CODE": 5,
      "BENE_COUNTY_CD": 600,
      "n_fills": 2273,
      "n_patients": 108,
      "pct_late": 75.8,
      "mean_risk": 0.519,
      "n_high": 1202,
      "pct_high": 52.9
    },
    {
      "SP_STATE_CODE": 8,
      "BENE_COUNTY_CD": 10,
      "n_fills": 2267,
      "n_patients": 103,
      "pct_late": 73.5,
      "mean_risk": 0.514,
      "n_high": 1221,
      "pct_high": 53.9
    },
    {
      "SP_STATE_CODE": 31,
      "BENE_COUNTY_CD": 160,
      "n_fills": 2245,
      "n_patients": 97,
      "pct_late": 75.3,
      "mean_risk": 0.522,
      "n_high": 1214,
      "pct_high": 54.1
    },
    {
      "SP_STATE_CODE": 6,
      "BENE_COUNTY_CD": 200,
      "n_fills": 2240,
      "n_patients": 116,
      "pct_late": 76.8,
      "mean_risk": 0.532,
      "n_high": 1255,
      "pct_high": 56.0
    },
    {
      "SP_STATE_CODE": 15,
      "BENE_COUNTY_CD": 440,
      "n_fills": 2203,
      "n_patients": 100,
      "pct_late": 74.3,
      "mean_risk": 0.516,
      "n_high": 1186,
      "pct_high": 53.8
    },
    {
      "SP_STATE_CODE": 39,
      "BENE_COUNTY_CD": 480,
      "n_fills": 2203,
      "n_patients": 105,
      "pct_late": 77.4,
      "mean_risk": 0.53,
      "n_high": 1226,
      "pct_high": 55.7
    },
    {
      "SP_STATE_CODE": 45,
      "BENE_COUNTY_CD": 650,
      "n_fills": 2201,
      "n_patients": 106,
      "pct_late": 76.4,
      "mean_risk": 0.526,
      "n_high": 1234,
      "pct_high": 56.1
    },
    {
      "SP_STATE_CODE": 44,
      "BENE_COUNTY_CD": 320,
      "n_fills": 2190,
      "n_patients": 95,
      "pct_late": 77.6,
      "mean_risk": 0.531,
      "n_high": 1217,
      "pct_high": 55.6
    },
    {
      "SP_STATE_CODE": 34,
      "BENE_COUNTY_CD": 330,
      "n_fills": 2152,
      "n_patients": 82,
      "pct_late": 74.7,
      "mean_risk": 0.517,
      "n_high": 1186,
      "pct_high": 55.1
    },
    {
      "SP_STATE_CODE": 22,
      "BENE_COUNTY_CD": 150,
      "n_fills": 2138,
      "n_patients": 107,
      "pct_late": 77.4,
      "mean_risk": 0.536,
      "n_high": 1205,
      "pct_high": 56.4
    },
    {
      "SP_STATE_CODE": 10,
      "BENE_COUNTY_CD": 100,
      "n_fills": 2133,
      "n_patients": 99,
      "pct_late": 76.5,
      "mean_risk": 0.524,
      "n_high": 1157,
      "pct_high": 54.2
    },
    {
      "SP_STATE_CODE": 1,
      "BENE_COUNTY_CD": 480,
      "n_fills": 2115,
      "n_patients": 107,
      "pct_late": 76.4,
      "mean_risk": 0.526,
      "n_high": 1169,
      "pct_high": 55.3
    },
    {
      "SP_STATE_CODE": 5,
      "BENE_COUNTY_CD": 590,
      "n_fills": 2107,
      "n_patients": 108,
      "pct_late": 74.9,
      "mean_risk": 0.525,
      "n_high": 1160,
      "pct_high": 55.1
    },
    {
      "SP_STATE_CODE": 19,
      "BENE_COUNTY_CD": 160,
      "n_fills": 2104,
      "n_patients": 87,
      "pct_late": 75.5,
      "mean_risk": 0.53,
      "n_high": 1181,
      "pct_high": 56.1
    },
    {
      "SP_STATE_CODE": 5,
      "BENE_COUNTY_CD": 520,
      "n_fills": 2100,
      "n_patients": 103,
      "pct_late": 75.5,
      "mean_risk": 0.521,
      "n_high": 1107,
      "pct_high": 52.7
    },
    {
      "SP_STATE_CODE": 36,
      "BENE_COUNTY_CD": 490,
      "n_fills": 2086,
      "n_patients": 99,
      "pct_late": 75.3,
      "mean_risk": 0.528,
      "n_high": 1161,
      "pct_high": 55.7
    },
    {
      "SP_STATE_CODE": 39,
      "BENE_COUNTY_CD": 470,
      "n_fills": 2085,
      "n_patients": 94,
      "pct_late": 77.1,
      "mean_risk": 0.533,
      "n_high": 1173,
      "pct_high": 56.3
    },
    {
      "SP_STATE_CODE": 31,
      "BENE_COUNTY_CD": 320,
      "n_fills": 2064,
      "n_patients": 91,
      "pct_late": 76.2,
      "mean_risk": 0.523,
      "n_high": 1129,
      "pct_high": 54.7
    },
    {
      "SP_STATE_CODE": 21,
      "BENE_COUNTY_CD": 160,
      "n_fills": 2036,
      "n_patients": 91,
      "pct_late": 76.9,
      "mean_risk": 0.523,
      "n_high": 1112,
      "pct_high": 54.6
    },
    {
      "SP_STATE_CODE": 6,
      "BENE_COUNTY_CD": 20,
      "n_fills": 2029,
      "n_patients": 96,
      "pct_late": 77.1,
      "mean_risk": 0.532,
      "n_high": 1135,
      "pct_high": 55.9
    },
    {
      "SP_STATE_CODE": 14,
      "BENE_COUNTY_CD": 989,
      "n_fills": 2014,
      "n_patients": 94,
      "pct_late": 75.5,
      "mean_risk": 0.533,
      "n_high": 1128,
      "pct_high": 56.0
    },
    {
      "SP_STATE_CODE": 10,
      "BENE_COUNTY_CD": 550,
      "n_fills": 2010,
      "n_patients": 85,
      "pct_late": 75.6,
      "mean_risk": 0.522,
      "n_high": 1107,
      "pct_high": 55.1
    },
    {
      "SP_STATE_CODE": 31,
      "BENE_COUNTY_CD": 300,
      "n_fills": 2001,
      "n_patients": 96,
      "pct_late": 75.0,
      "mean_risk": 0.531,
      "n_high": 1124,
      "pct_high": 56.2
    },
    {
      "SP_STATE_CODE": 9,
      "BENE_COUNTY_CD": 0,
      "n_fills": 1991,
      "n_patients": 113,
      "pct_late": 77.3,
      "mean_risk": 0.536,
      "n_high": 1137,
      "pct_high": 57.1
    },
    {
      "SP_STATE_CODE": 5,
      "BENE_COUNTY_CD": 580,
      "n_fills": 1961,
      "n_patients": 80,
      "pct_late": 74.6,
      "mean_risk": 0.516,
      "n_high": 1048,
      "pct_high": 53.4
    },
    {
      "SP_STATE_CODE": 45,
      "BENE_COUNTY_CD": 310,
      "n_fills": 1958,
      "n_patients": 82,
      "pct_late": 73.1,
      "mean_risk": 0.511,
      "n_high": 1024,
      "pct_high": 52.3
    },
    {
      "SP_STATE_CODE": 54,
      "BENE_COUNTY_CD": 0,
      "n_fills": 1957,
      "n_patients": 78,
      "pct_late": 75.5,
      "mean_risk": 0.52,
      "n_high": 1086,
      "pct_high": 55.5
    },
    {
      "SP_STATE_CODE": 11,
      "BENE_COUNTY_CD": 530,
      "n_fills": 1938,
      "n_patients": 85,
      "pct_late": 76.2,
      "mean_risk": 0.517,
      "n_high": 1061,
      "pct_high": 54.7
    },
    {
      "SP_STATE_CODE": 6,
      "BENE_COUNTY_CD": 290,
      "n_fills": 1938,
      "n_patients": 102,
      "pct_late": 76.3,
      "mean_risk": 0.526,
      "n_high": 1077,
      "pct_high": 55.6
    },
    {
      "SP_STATE_CODE": 5,
      "BENE_COUNTY_CD": 210,
      "n_fills": 1920,
      "n_patients": 90,
      "pct_late": 76.4,
      "mean_risk": 0.526,
      "n_high": 1049,
      "pct_high": 54.6
    },
    {
      "SP_STATE_CODE": 3,
      "BENE_COUNTY_CD": 120,
      "n_fills": 1863,
      "n_patients": 80,
      "pct_late": 74.8,
      "mean_risk": 0.526,
      "n_high": 985,
      "pct_high": 52.9
    },
    {
      "SP_STATE_CODE": 52,
      "BENE_COUNTY_CD": 660,
      "n_fills": 1857,
      "n_patients": 82,
      "pct_late": 75.4,
      "mean_risk": 0.514,
      "n_high": 987,
      "pct_high": 53.2
    },
    {
      "SP_STATE_CODE": 42,
      "BENE_COUNTY_CD": 410,
      "n_fills": 1820,
      "n_patients": 69,
      "pct_late": 76.8,
      "mean_risk": 0.52,
      "n_high": 977,
      "pct_high": 53.7
    },
    {
      "SP_STATE_CODE": 16,
      "BENE_COUNTY_CD": 760,
      "n_fills": 1811,
      "n_patients": 85,
      "pct_late": 76.1,
      "mean_risk": 0.531,
      "n_high": 1007,
      "pct_high": 55.6
    },
    {
      "SP_STATE_CODE": 42,
      "BENE_COUNTY_CD": 220,
      "n_fills": 1805,
      "n_patients": 89,
      "pct_late": 75.7,
      "mean_risk": 0.523,
      "n_high": 986,
      "pct_high": 54.6
    },
    {
      "SP_STATE_CODE": 39,
      "BENE_COUNTY_CD": 210,
      "n_fills": 1797,
      "n_patients": 81,
      "pct_late": 74.7,
      "mean_risk": 0.513,
      "n_high": 954,
      "pct_high": 53.1
    },
    {
      "SP_STATE_CODE": 39,
      "BENE_COUNTY_CD": 590,
      "n_fills": 1794,
      "n_patients": 83,
      "pct_late": 78.2,
      "mean_risk": 0.538,
      "n_high": 1019,
      "pct_high": 56.8
    },
    {
      "SP_STATE_CODE": 39,
      "BENE_COUNTY_CD": 750,
      "n_fills": 1781,
      "n_patients": 76,
      "pct_late": 75.7,
      "mean_risk": 0.521,
      "n_high": 979,
      "pct_high": 55.0
    },
    {
      "SP_STATE_CODE": 5,
      "BENE_COUNTY_CD": 410,
      "n_fills": 1758,
      "n_patients": 83,
      "pct_late": 76.6,
      "mean_risk": 0.528,
      "n_high": 975,
      "pct_high": 55.5
    },
    {
      "SP_STATE_CODE": 39,
      "BENE_COUNTY_CD": 320,
      "n_fills": 1753,
      "n_patients": 84,
      "pct_late": 76.4,
      "mean_risk": 0.531,
      "n_high": 977,
      "pct_high": 55.7
    },
    {
      "SP_STATE_CODE": 21,
      "BENE_COUNTY_CD": 10,
      "n_fills": 1732,
      "n_patients": 83,
      "pct_late": 75.3,
      "mean_risk": 0.522,
      "n_high": 946,
      "pct_high": 54.6
    },
    {
      "SP_STATE_CODE": 22,
      "BENE_COUNTY_CD": 0,
      "n_fills": 1719,
      "n_patients": 78,
      "pct_late": 75.8,
      "mean_risk": 0.531,
      "n_high": 970,
      "pct_high": 56.4
    },
    {
      "SP_STATE_CODE": 14,
      "BENE_COUNTY_CD": 530,
      "n_fills": 1709,
      "n_patients": 88,
      "pct_late": 77.7,
      "mean_risk": 0.525,
      "n_high": 968,
      "pct_high": 56.6
    },
    {
      "SP_STATE_CODE": 38,
      "BENE_COUNTY_CD": 190,
      "n_fills": 1705,
      "n_patients": 87,
      "pct_late": 74.9,
      "mean_risk": 0.522,
      "n_high": 893,
      "pct_high": 52.4
    },
    {
      "SP_STATE_CODE": 15,
      "BENE_COUNTY_CD": 10,
      "n_fills": 1685,
      "n_patients": 70,
      "pct_late": 77.7,
      "mean_risk": 0.529,
      "n_high": 933,
      "pct_high": 55.4
    },
    {
      "SP_STATE_CODE": 5,
      "BENE_COUNTY_CD": 550,
      "n_fills": 1652,
      "n_patients": 70,
      "pct_late": 75.5,
      "mean_risk": 0.513,
      "n_high": 862,
      "pct_high": 52.2
    },
    {
      "SP_STATE_CODE": 50,
      "BENE_COUNTY_CD": 310,
      "n_fills": 1639,
      "n_patients": 81,
      "pct_late": 77.2,
      "mean_risk": 0.517,
      "n_high": 872,
      "pct_high": 53.2
    },
    {
      "SP_STATE_CODE": 14,
      "BENE_COUNTY_CD": 900,
      "n_fills": 1633,
      "n_patients": 67,
      "pct_late": 75.1,
      "mean_risk": 0.52,
      "n_high": 888,
      "pct_high": 54.4
    },
    {
      "SP_STATE_CODE": 38,
      "BENE_COUNTY_CD": 20,
      "n_fills": 1622,
      "n_patients": 90,
      "pct_late": 75.3,
      "mean_risk": 0.508,
      "n_high": 844,
      "pct_high": 52.0
    },
    {
      "SP_STATE_CODE": 5,
      "BENE_COUNTY_CD": 640,
      "n_fills": 1621,
      "n_patients": 72,
      "pct_late": 76.7,
      "mean_risk": 0.536,
      "n_high": 909,
      "pct_high": 56.1
    },
    {
      "SP_STATE_CODE": 36,
      "BENE_COUNTY_CD": 510,
      "n_fills": 1605,
      "n_patients": 72,
      "pct_late": 74.9,
      "mean_risk": 0.523,
      "n_high": 872,
      "pct_high": 54.3
    },
    {
      "SP_STATE_CODE": 3,
      "BENE_COUNTY_CD": 70,
      "n_fills": 1597,
      "n_patients": 76,
      "pct_late": 76.5,
      "mean_risk": 0.527,
      "n_high": 888,
      "pct_high": 55.6
    },
    {
      "SP_STATE_CODE": 19,
      "BENE_COUNTY_CD": 350,
      "n_fills": 1590,
      "n_patients": 68,
      "pct_late": 76.0,
      "mean_risk": 0.526,
      "n_high": 876,
      "pct_high": 55.1
    },
    {
      "SP_STATE_CODE": 26,
      "BENE_COUNTY_CD": 910,
      "n_fills": 1580,
      "n_patients": 71,
      "pct_late": 75.4,
      "mean_risk": 0.525,
      "n_high": 877,
      "pct_high": 55.5
    },
    {
      "SP_STATE_CODE": 19,
      "BENE_COUNTY_CD": 80,
      "n_fills": 1565,
      "n_patients": 74,
      "pct_late": 76.9,
      "mean_risk": 0.532,
      "n_high": 898,
      "pct_high": 57.4
    },
    {
      "SP_STATE_CODE": 36,
      "BENE_COUNTY_CD": 790,
      "n_fills": 1559,
      "n_patients": 74,
      "pct_late": 77.3,
      "mean_risk": 0.528,
      "n_high": 859,
      "pct_high": 55.1
    },
    {
      "SP_STATE_CODE": 5,
      "BENE_COUNTY_CD": 500,
      "n_fills": 1545,
      "n_patients": 67,
      "pct_late": 74.3,
      "mean_risk": 0.522,
      "n_high": 825,
      "pct_high": 53.4
    },
    {
      "SP_STATE_CODE": 45,
      "BENE_COUNTY_CD": 801,
      "n_fills": 1544,
      "n_patients": 66,
      "pct_late": 75.6,
      "mean_risk": 0.52,
      "n_high": 805,
      "pct_high": 52.1
    },
    {
      "SP_STATE_CODE": 10,
      "BENE_COUNTY_CD": 70,
      "n_fills": 1540,
      "n_patients": 65,
      "pct_late": 78.0,
      "mean_risk": 0.526,
      "n_high": 830,
      "pct_high": 53.9
    },
    {
      "SP_STATE_CODE": 1,
      "BENE_COUNTY_CD": 440,
      "n_fills": 1539,
      "n_patients": 62,
      "pct_late": 75.7,
      "mean_risk": 0.521,
      "n_high": 855,
      "pct_high": 55.6
    },
    {
      "SP_STATE_CODE": 26,
      "BENE_COUNTY_CD": 950,
      "n_fills": 1530,
      "n_patients": 71,
      "pct_late": 75.1,
      "mean_risk": 0.516,
      "n_high": 815,
      "pct_high": 53.3
    },
    {
      "SP_STATE_CODE": 39,
      "BENE_COUNTY_CD": 280,
      "n_fills": 1527,
      "n_patients": 69,
      "pct_late": 76.7,
      "mean_risk": 0.525,
      "n_high": 843,
      "pct_high": 55.2
    },
    {
      "SP_STATE_CODE": 39,
      "BENE_COUNTY_CD": 270,
      "n_fills": 1524,
      "n_patients": 67,
      "pct_late": 75.6,
      "mean_risk": 0.525,
      "n_high": 818,
      "pct_high": 53.7
    },
    {
      "SP_STATE_CODE": 31,
      "BENE_COUNTY_CD": 0,
      "n_fills": 1522,
      "n_patients": 67,
      "pct_late": 75.4,
      "mean_risk": 0.513,
      "n_high": 789,
      "pct_high": 51.8
    },
    {
      "SP_STATE_CODE": 25,
      "BENE_COUNTY_CD": 240,
      "n_fills": 1514,
      "n_patients": 58,
      "pct_late": 75.0,
      "mean_risk": 0.518,
      "n_high": 824,
      "pct_high": 54.4
    },
    {
      "SP_STATE_CODE": 5,
      "BENE_COUNTY_CD": 370,
      "n_fills": 1512,
      "n_patients": 68,
      "pct_late": 75.9,
      "mean_risk": 0.52,
      "n_high": 824,
      "pct_high": 54.5
    },
    {
      "SP_STATE_CODE": 49,
      "BENE_COUNTY_CD": 921,
      "n_fills": 1507,
      "n_patients": 57,
      "pct_late": 76.0,
      "mean_risk": 0.523,
      "n_high": 816,
      "pct_high": 54.1
    },
    {
      "SP_STATE_CODE": 10,
      "BENE_COUNTY_CD": 400,
      "n_fills": 1505,
      "n_patients": 72,
      "pct_late": 78.1,
      "mean_risk": 0.536,
      "n_high": 856,
      "pct_high": 56.9
    },
    {
      "SP_STATE_CODE": 15,
      "BENE_COUNTY_CD": 700,
      "n_fills": 1490,
      "n_patients": 58,
      "pct_late": 74.6,
      "mean_risk": 0.522,
      "n_high": 831,
      "pct_high": 55.8
    },
    {
      "SP_STATE_CODE": 5,
      "BENE_COUNTY_CD": 30,
      "n_fills": 1484,
      "n_patients": 65,
      "pct_late": 76.5,
      "mean_risk": 0.523,
      "n_high": 827,
      "pct_high": 55.7
    },
    {
      "SP_STATE_CODE": 54,
      "BENE_COUNTY_CD": 640,
      "n_fills": 1474,
      "n_patients": 60,
      "pct_late": 77.1,
      "mean_risk": 0.525,
      "n_high": 810,
      "pct_high": 55.0
    }
  ],
  "totals": {
    "n_states": 52,
    "n_counties": 2978,
    "total_fills": 1473595,
    "total_patients": 67085
  }
}